
<annotation>
    <folder>images</folder>
    <filename>Cars43.png</filename>
    <size>
        <width>471</width>
        <height>270</height>
        <depth>3</depth>
    </size>
    <segmented>0</segmented>
    <object>
        <name>licence</name>
        <pose>Unspecified</pose>
        <truncated>0</truncated>
        <occluded>0</occluded>
        <difficult>0</difficult>
        <bndbox>
            <xmin>142</xmin>
            <ymin>111</ymin>
            <xmax>319</xmax>
            <ymax>161</ymax>
        </bndbox>
    </object>
</annotation>